{
    "type": "immersiveengineering:sawmill",
    "energy": 1600,
    "input": [
        {
            "item": "quark:ancient_log"
        },
        {
            "item": "quark:ancient_wood"
        }
    ],
    "result": {
        "count": 6,
        "item": "quark:ancient_planks"
    },
    "secondaries": [
        {
            "output": {
                "tag": "forge:dusts/wood"
            },
            "stripping": true
        },
        {
            "output": {
                "tag": "forge:dusts/wood"
            },
            "stripping": false
        }
    ],
    "stripped": {
        "item": "quark:stripped_ancient_log"
    },
  "conditions": [
    {
      "type": "quark:flag",
      "flag": "ancient_wood"
    }
  ]
}